{"word": "abnegation", "accent": "/\u02cc\u00e6bn\u026a\u02c8\u0261e\u026a\u0283n/", "mean_cn": "n. \u514b\u5236\uff0c\u81ea\u6211\u514b\u5236\uff0c\u653e\u5f03", "mean_en": "the denial and rejection of a doctrine or belief", "sentence": "He makes an abnegation of his father's property and legacy.", "sentence_trans": "\u4ed6\u653e\u5f03\u4e86\u5bf9\u4ed6\u7236\u4eb2\u7684\u8d22\u4ea7\u548c\u9057\u4ea7\u7ee7\u627f\u6743\u3002", "sentence_phrase": "", "word_etyma": "abnegat(e)\u62d2\u7edd + ion\u540d\u8bcd\u540e\u7f00 \u2192 abnegation \u62d2\u7edd", "cloze_data": {"syllable": "ab-ne-ga-tion", "cloze": "ab-ne-g[a]-t[ion]", "options": ["e|i|o|u", "ing|ang|ong|ung"], "tips": [["g[a]", "alg[a]"], ["act[ion]", "dat[ion]"]]}}