{"word": "adroit", "accent": "/\u0259\u02c8dr\u0254\u026at/", "mean_cn": "adj. \u719f\u7ec3\u7684\uff0c\u7075\u5de7\u7684", "mean_en": "very clever or skillful", "sentence": "The chef is adroit in using kitchen knives.", "sentence_trans": "\u8fd9\u4f4d\u5927\u53a8\u83dc\u5200\u7528\u7684\u76f8\u5f53\u719f\u7ec3\u3002\uff08\u5200\u5de5\u68d2\u68d2\u54d2\uff01\uff09", "sentence_phrase": "is adroit in", "word_etyma": "", "cloze_data": {"syllable": "adroit", "cloze": "adr[oi]t", "options": ["oa|oe|oy|oo|o"], "tips": [["adr[oi]tly", "maladr[oi]t"]]}}