{"word": "autocracy", "accent": "/\u0254\u02d0\u02c8t\u0251\u02d0kr\u0259si/", "mean_cn": "n. \u72ec\u88c1\u7edf\u6cbb\u7684\u56fd\u5bb6\uff1b\u4e13\u5236\u653f\u6cbb", "mean_en": "a country that is ruled by a person or group with total power", "sentence": "Ancient Egypt was an autocracy ruled by Pharaoh.", "sentence_trans": "\u53e4\u57c3\u53ca\u662f\u4e00\u4e2a\u7531\u6cd5\u8001\u7edf\u6cbb\u7684\u72ec\u88c1\u56fd\u5bb6\u3002", "sentence_phrase": "", "word_etyma": "auto\u81ea\u5df1+cracy\u7edf\u6cbb \u2192 \u4e13\u5236", "cloze_data": {"syllable": "au-toc-ra-cy", "cloze": "[au]-t[o]c-ra-cy", "options": ["ae|ao|eu|ou|ow|a|o", "a|e|i|u"], "tips": [["[au]ra", "[au]ca"], ["est[o]c", "Nost[o]c"]]}}