{"word": "comical", "accent": "/\u02c8k\u0251\u02d0m\u026akl/", "mean_cn": "adj. \u6ed1\u7a3d\u7684\uff0c\u53ef\u7b11\u7684", "mean_en": "funny or amusing, especially because it is strange or ridiculous", "sentence": "That little dog is very comical.", "sentence_trans": "\u8fd9\u53ea\u5c0f\u72d7\u5f88\u6ed1\u7a3d\u3002", "sentence_phrase": "", "word_etyma": "comic\u559c\u5267\u7684 + al...\u7684 \u2192 adj. \u6ed1\u7a3d\u7684\uff0c\u597d\u7b11\u7684", "cloze_data": {"syllable": "co-mi-cal", "cloze": "co-mi-c[al]", "options": ["el|le|nl|ol"], "tips": [["Uc[al]", "c[al]"]]}}