{"word": "cordon", "accent": "/\u02c8k\u0254\u02d0rdn/", "mean_cn": "n. \u54e8\u5175\u7ebf\uff0c\u8b66\u6212\u7ebf\uff1b  v. \u5e03\u8bbe\u8b66\u6212\u7ebf", "mean_en": "a line of people or objects that are placed around or in front of a person or place to keep people away", "sentence": "For your own safety, please do not cross the police cordon.", "sentence_trans": "\u4e3a\u4e86\u4f60\u7684\u81ea\u8eab\u5b89\u5168\uff0c\u8bf7\u4e0d\u8981\u8d8a\u8fc7\u8b66\u6212\u7ebf\u3002", "sentence_phrase": "the police cordon", "word_etyma": "cord\u7ef3\u7d22+on\u8868\u793a\u7269 \u2192\u9970\u5e26", "cloze_data": {"syllable": "cor-don", "cloze": "c[or]-don", "options": ["ar|er|ir|ur|a"], "tips": [["ac[or]", "c[or]"]]}}