{"word": "eclectic", "accent": "/\u026a\u02c8klekt\u026ak/", "mean_cn": "adj. \u6298\u8877\u4e3b\u4e49\u7684\uff0c\u9009\u62e9\u7684", "mean_en": "including things taken from many different sources", "sentence": "She has an eclectic taste in music. She listens to hip-hop, rock, and folk music.", "sentence_trans": "\u5979\u5bf9\u97f3\u4e50\u7684\u559c\u597d\u517c\u6536\u5e76\u84c4\uff0c\u5979\u5e73\u5e38\u542c\u563b\u54c8\u3001\u6447\u6eda\u3001\u4e61\u6751\u97f3\u4e50...", "sentence_phrase": "has an eclectic taste in", "word_etyma": "", "cloze_data": {"syllable": "e-clec-tic", "cloze": "e-[cle]c-tic", "options": ["tle|dle|ple|ble|gle|kle"], "tips": [["e[cle]ctism", "E[cle]ctics"]]}}