{"word": "enervate", "accent": "/\u02c8en\u0259rve\u026at/", "mean_cn": "v. \u4f7f\u865a\u5f31", "mean_en": "to make (someone or something) very weak or tired", "sentence": "Computer work enervated him: he wished he could do construction instead.", "sentence_trans": "\u7535\u8111\u5de5\u4f5c\u4f7f\u4ed6\u865a\u5f31\u65e0\u529b\uff0c\u4ed6\u53cd\u800c\u5e0c\u671b\u80fd\u591f\u4ece\u4e8b\u5efa\u7b51\u884c\u4e1a\u3002", "sentence_phrase": "", "word_etyma": "", "cloze_data": {"syllable": "en-er-vate", "cloze": "en-[er]-vate", "options": ["ar|ir|or|ur|a"], "tips": [["[er]", "o[er]"]]}}