{"word": "ethereal", "accent": "/i\u02c8\u03b8\u026ari\u0259l/", "mean_cn": "adj. \u592a\u7a7a\u7684\uff0c\u8f7b\u5de7\u7684\uff0c\u50cf\u7a7a\u6c14\u7684", "mean_en": "", "sentence": "Her ethereal beauty is something to behold.", "sentence_trans": "\u5979\u7684\u98d8\u9038\u4e4b\u7f8e\u663e\u800c\u6613\u89c1\u3002", "sentence_phrase": "", "word_etyma": "ethere=ether\u82cd\u5929 \uff0b al...\u7684 \u2192 ethereal\u5929\u4e0a\u7684\uff1b\u8f7b\u7684", "cloze_data": {"syllable": "ethe-re-al", "cloze": "e[th]e-re-al", "options": ["tch|chr|sch|sh"], "tips": [["e[th]erify", "e[th]erion"]]}}