{"word": "execrate", "accent": "/'eks\u026a\u02cckre\u026at/", "mean_cn": "v. \u8c34\u8d23\uff0c\u75db\u6068", "mean_en": "to dislike and criticize (someone or something) very strongly", "sentence": "His peers execrated him - why, I don't know, maybe his glasses.", "sentence_trans": "\u4ed6\u7684\u540c\u9f84\u4eba\u4eec\u8c34\u8d23\u4ed6-\u4e3a\u4ec0\u4e48\uff1f\u6211\u4e0d\u77e5\u9053\uff0c\u53ef\u80fd\u662f\u4ed6\u7684\u773c\u955c\u5427\uff01", "sentence_phrase": "", "word_etyma": "", "cloze_data": {"syllable": "e-xe-crate", "cloze": "e-x[e]-crate", "options": ["a|i|o|u"], "tips": [["x[e]bec", "x[e]nia"]]}}