{"word": "hidebound", "accent": "/\u02c8ha\u026adba\u028and/", "mean_cn": "adj. \u6b7b\u677f\u7684\uff0c\u987d\u56fa\u7684\uff0c\u58a8\u5b88\u6210\u89c4\u7684", "mean_en": "not willing to accept new or different ideas", "sentence": "This hidebound man refused to use the application on the phone to direct him.", "sentence_trans": "\u8fd9\u4e2a\u987d\u56fa\u7684\u7537\u4eba\u62d2\u7edd\u4f7f\u7528\u624b\u673a\u4e0a\u7684\u8f6f\u4ef6\u4e3a\u4ed6\u6307\u8def\u3002", "sentence_phrase": "", "word_etyma": "", "cloze_data": {"syllable": "hide-bound", "cloze": "hide-b[ou]nd", "options": ["ae|ao|au|eu|ow|a|o"], "tips": [["b[ou]nded", "b[ou]nden"]]}}