{"word": "indefatigable", "accent": "/\u02cc\u026and\u026a\u02c8f\u00e6t\u026a\u0261\u0259bl/", "mean_cn": "adj. \u4e0d\u5c48\u4e0d\u6320\u7684\uff1b\u4e0d\u77e5\u75b2\u5026\u7684", "mean_en": "able to work or continue for a very long time without becoming tired", "sentence": "She was indefatigable in her quest to run non-stop across the U.S.", "sentence_trans": "\u4e3a\u4e86\u4e0d\u95f4\u65ad\u5730\u8dd1\u904d\u7f8e\u56fd\u5404\u5730\uff0c\u5979\u4e0d\u77e5\u75b2\u5026\u3002", "sentence_phrase": "", "word_etyma": "in\u4e0d \uff0b de\u52a0\u5f3a\u610f\u4e49 \uff0b fatig=weary\u75b2\u5026 \uff0b able...\u7684 \u2192 indefatigable\u4e0d\u77e5\u75b2\u5026\u7684", "cloze_data": {"syllable": "in-de-fati-ga-ble", "cloze": "[in]-de-fati-ga-[ble]", "options": ["en|on|un|an|e|i|a|o|u", "tle|dle|ple|cle|gle|kle"], "tips": [["[in]", "[in]by"], ["ca[ble]", "am[ble]"]]}}