{"word": "lasting", "accent": "/\u02c8l\u00e6st\u026a\u014b/", "mean_cn": "n. \u7ed3\u5b9e\u7684\u659c\u7eb9\u5e03\uff0c\u8010\u4e45\u529b\uff1b  adj. \u6301\u4e45\u7684\uff0c\u6c38\u4e45\u7684", "mean_en": "existing or continuing for a long time", "sentence": "Their love was a lasting one - they had been married for forty years.", "sentence_trans": "\u4ed6\u4eec\u7684\u7231\u975e\u5e38\u6301\u4e45\u2014\u4ed6\u4eec\u5df2\u7ecf\u7ed3\u5a5a\u56db\u5341\u5e74\u4e86\u3002", "sentence_phrase": "a lasting one", "word_etyma": "last\u6301\u4e45 + ing \u5f62\u5bb9\u8bcd\u540e\u7f00 \u2192lasting\u6301\u4e45\u7684", "cloze_data": {"syllable": "last-ing", "cloze": "last-[ing]", "options": ["ion|ang|ong|ung"], "tips": [["[ing]", "ap[ing]"]]}}