{"word": "misdemeanor", "accent": "/\u02ccm\u026asd\u026a'mi\u02d0n\u0259/", "mean_cn": "n. \u8f7b\u7f6a\uff0c\u54c1\u884c\u4e0d\u7aef", "mean_en": "a crime that is not very serious :a crime that is less serious than a felony", "sentence": "Being drunk in public is just a misdemeanor; resisting arrest is a felony.", "sentence_trans": "\u516c\u5171\u573a\u6240\u9189\u9152\u53ea\u662f\u8f7b\u7f6a\uff0c\u62b5\u6297\u902e\u6355\u5c31\u662f\u91cd\u7f6a\u4e86\u3002", "sentence_phrase": "", "word_etyma": "", "cloze_data": {"syllable": "mis-de-meanor", "cloze": "mis-de-mean[or]", "options": ["ar|er|ir|ur|a"], "tips": [["demean[or]"]]}}