{"word": "munificent", "accent": "/mju\u02d0\u02c8n\u026af\u026asnt/", "mean_cn": "adj. \u6177\u6168\u7684\uff0c\u5927\u65b9\u7684", "mean_en": "very generous", "sentence": "Santa is so munificent that he gives gifts to millions of children every year.", "sentence_trans": "\u5723\u8bde\u8001\u4eba\u771f\u5927\u65b9\uff0c\u4ed6\u6bcf\u5e74\u7ed9\u6570\u767e\u4e07\u513f\u7ae5\u9001\u793c\u7269\u3002", "sentence_phrase": "", "word_etyma": "muni\u516c\u5171\u7684 + fic\u505a + ent\u5f62\u5bb9\u8bcd\u540e\u7f00 \u2192 \u505a\u51fa\u6765\u7ed9\u5927\u5bb6 \u2192 munificent\u6177\u6168\u7684", "cloze_data": {"syllable": "mu-ni-fi-cent", "cloze": "mu-ni-f[i]-c[en]t", "options": ["a|e|o|u", "in|on|un|an|e|i|a|o|u"], "tips": [["f[i]", "f[i]at"], ["asc[en]t", "c[en]t"]]}}