{"word": "ornate", "accent": "/\u0254\u02d0r\u02c8ne\u026at/", "mean_cn": "adj. \u4fee\u8f9e\u4e0a\u6781\u8003\u7a76\u7684\uff1b\u88c5\u9970\u534e\u4e3d\u7684", "mean_en": "covered with decorations :covered with fancy patterns and shapes", "sentence": "These designs are too ornate--do you have anything simpler?", "sentence_trans": "\u8fd9\u4e9b\u8bbe\u8ba1\u592a\u8fc7\u534e\u4e3d\uff0c\u4f60\u6709\u7a0d\u5fae\u6734\u7d20\u4e00\u70b9\u7684\u5417\uff1f", "sentence_phrase": "", "word_etyma": "orn\u88c5\u9970+ate\u5f62\u5bb9\u8bcd\u540e\u7f00 \u2192 \u534e\u4e3d\u7684\uff1b\u88c5\u9970\u7684", "cloze_data": {"syllable": "or-nate", "cloze": "[or]-nate", "options": ["ar|er|ir|ur|a"], "tips": [["[or]", "[or]by"]]}}