{"word": "peerless", "accent": "/\u02c8p\u026arl\u0259s/", "mean_cn": "adj. \u65e0\u4e0e\u4f26\u6bd4\u7684\uff0c\u65e0\u53ef\u5339\u654c\u7684", "mean_en": "having no equal :better than all others", "sentence": "She received a great deal of applause after her peerless performance.", "sentence_trans": "\u5728\u5979\u65e0\u4e0e\u4f26\u6bd4\u7684\u8868\u6f14\u4e4b\u540e\uff0c\u5979\u6536\u5230\u4e86\u5927\u91cf\u7684\u559d\u5f69\u3002", "sentence_phrase": "her peerless performance", "word_etyma": "peer\u540c\u7b49\u7684 + less\u65e0 \u2192 peerless \u65e0\u4e0e\u4f26\u6bd4\u7684", "cloze_data": {"syllable": "peer-less", "cloze": "p[eer]-less", "options": ["ear|ier|eir|air"], "tips": [["p[eer]ly", "outp[eer]"]]}}