{"word": "prelate", "accent": "/\u02c8prel\u0259t/", "mean_cn": "n. \u9ad8\u4f4d\u795e\u804c\u8005\uff1b\u9ad8\u7ea7\u6559\u58eb", "mean_en": "a high-ranking Christian priest :a bishop, cardinal, etc.", "sentence": "Pope John Paul II was a prelate in the Catholic Church before he became pope.", "sentence_trans": "\u5728\u7ea6\u7ff0\u4fdd\u7f57\u4e8c\u4e16\u6210\u4e3a\u6559\u7687\u4e4b\u524d\uff0c\u4ed6\u66fe\u662f\u5929\u4e3b\u6559\u5802\u7684\u9ad8\u7ea7\u6559\u58eb\u3002", "sentence_phrase": "", "word_etyma": "", "cloze_data": {"syllable": "prelate", "cloze": "pr[el]ate", "options": ["al|le|nl|ol"], "tips": [["archpr[el]ate", "pr[el]atehood"]]}}