{"word": "primal", "accent": "/\u02c8pra\u026aml/", "mean_cn": "adj. \u539f\u59cb\u7684\uff0c\u6700\u521d\u7684\uff0c\u4e3b\u8981\u7684\uff1b  n. \u88ab\u538b\u6291\u7ae5\u5e74\u60c5\u7eea\u7684\u91ca\u653e\uff1b  vt. \u91ca\u653e", "mean_en": "very basic and powerful", "sentence": "A mother koala has a primal instinct to protect her baby.", "sentence_trans": "\u8003\u62c9\u5988\u5988\u6709\u79cd\u539f\u59cb\u672c\u80fd\u4f1a\u4fdd\u62a4\u5b83\u7684\u5b9d\u5b9d\u3002", "sentence_phrase": "a primal instinct", "word_etyma": "prim\u6700\u521d+al\u2026\u7684\u2192primal\u6700\u521d\u7684\uff0c\u539f\u59cb\u7684", "cloze_data": {"syllable": "pri-mal", "cloze": "pri-m[al]", "options": ["el|le|nl|ol"], "tips": [["m[al]", "dem[al]"]]}}