{"word": "quantum", "accent": "/\u02c8kw\u0251\u02d0nt\u0259m/", "mean_cn": "n. \u91cf\u5b50", "mean_en": "the smallest amount of many forms of energy (such as light)", "sentence": "When an electron drops one orbit level, a quantum of energy is released.", "sentence_trans": "\u5f53\u7535\u5b50\u964d\u4f4e\u8f68\u9053\u7684\u65f6\u5019\uff0c\u91cf\u5b50\u80fd\u91cf\u5c31\u4f1a\u88ab\u91ca\u653e\u51fa\u6765\u3002", "sentence_phrase": "a quantum of energy", "word_etyma": "", "cloze_data": {"syllable": "quan-tum", "cloze": "q[ua]n-tum", "options": ["uu|ue|ui|uo|iu|u"], "tips": [["q[ua]nta", "q[ua]n"]]}}