{"word": "revolutionize", "accent": "/\u02ccrev\u0259\u02c8lu\u02d0\u0283\u0259na\u026az/", "mean_cn": "v.\u5f7b\u5e95\u53d8\u9769\uff1b\u4f7f\u9769\u547d\u5316\uff1b  vt.\u704c\u8f93\u9769\u547d\u601d\u60f3", "mean_en": "to completely change the way that something is done", "sentence": "We have revolutionized the traditional way of learning English words!", "sentence_trans": "\u4f20\u7edf\u7684\u82f1\u8bed\u80cc\u5355\u8bcd\u65b9\u6cd5\u5df2\u88ab\u6211\u4eec\u5f7b\u5e95\u6539\u9769\u4e86\uff01", "sentence_phrase": "", "word_etyma": "revolution\u9769\u547d + ize\u8868\u52a8\u8bcd \u2192 \u53d1\u52a8\u9769\u547d", "cloze_data": {"syllable": "re-vo-lu-tion-ize", "cloze": "re-vo-l[u]-t[ion]-ize", "options": ["a|e|i|o", "ing|ang|ong|ung"], "tips": [["ul[u]", "hul[u]"], ["act[ion]", "dat[ion]"]]}}