{"word": "snug", "accent": "/sn\u028c\u0261/", "mean_cn": "adj. \u6e29\u6696\u7684\uff0c\u8212\u9002\u7684\uff1b  vt. \u4f7f\u6e29\u6696\u8212\u9002\uff1b  n. <\u82f1>\u9152\u5427\u91cc\u7684\u79c1\u623f\uff1b  vi. \u8212\u670d\u5730\u8737\u4f0f\uff0c\u504e\u4f9d", "mean_en": "warm, comfortable and protected, especially from the cold", "sentence": "They love lying beside the snug fire to celebrate Christmas.", "sentence_trans": "\u4ed6\u4eec\u559c\u6b22\u8eba\u5728\u6e29\u6696\u7684\u7089\u706b\u65c1\u6765\u5e86\u795d\u5723\u8bde\u8282\u3002", "sentence_phrase": "", "word_etyma": "", "cloze_data": {"syllable": "snug", "cloze": "sn[u]g", "options": ["a|e|i|o"], "tips": [["sn[u]gly", "sn[u]gness"]]}}