{"word": "splice", "accent": "/spla\u026as/", "mean_cn": "v. \u63a5\u5934\uff0c\u637b\u63a5\uff08\u7ebf\u5934\u7b49\uff09\uff1b  n. \u63a5\u5408\uff0c\u8854\u63a5\u5904", "mean_en": "to join ropes, wires, etc., by weaving or twisting them together", "sentence": "The figure-8 knot is a good way to splice two ropes together.", "sentence_trans": "8\u5b57\u7ed3\u662f\u628a\u4e24\u6761\u7ef3\u5b50\u637b\u63a5\u8d77\u6765\u7684\u597d\u65b9\u6cd5\u3002", "sentence_phrase": "", "word_etyma": "spl\u5206\u88c2 \uff0b ice\u8868\u540d\u8bcd\uff0c\u884c\u4e3a\uff0c\u72b6\u6001 \u2192 splice\u7531\u5206\u88c2\u63a8\u6210\u8854\u63a5", "cloze_data": {"syllable": "splice", "cloze": "splic[e]", "options": ["a|i|o|u"], "tips": [["resplic[e]", "splic[e]able"]]}}