{"word": "surpassingly", "accent": "/s\u0259'p\u0251\u02d0s\u026a\u014bl\u026a/", "mean_cn": "adv. \u8d85\u7fa4\u5730\uff0c\u5353\u8d8a\u5730", "mean_en": " to a surpassing degree", "sentence": "He is a surpassingly effective salesman.", "sentence_trans": "\u4ed6\u662f\u4e2a\u6548\u7387\u8d85\u7fa4\u7684\u9500\u552e\u5458\u3002", "sentence_phrase": "surpassingly effective", "word_etyma": "surpass\u8d85\u8fc7 + ing\u5f62\u5bb9\u8bcd\u540e\u7f00 + ly\u526f\u8bcd\u540e\u7f00 \u2192 surpassingly \u8d85\u7fa4\u5730\uff0c\u5353\u8d8a\u5730", "cloze_data": {"syllable": "sur-pass-ing-ly", "cloze": "s[ur]-pass-[ing]-ly", "options": ["ar|er|ir|or|a", "ion|ang|ong|ung"], "tips": [["s[ur]", "s[ur]al"], ["[ing]", "ap[ing]"]]}}