{"word": "tanner", "accent": "/\u02c8t\u00e6n\u0259r/", "mean_cn": "n. \u5236\u9769\u5de5\u4eba\uff0c\u516d\u4fbf\u58eb", "mean_en": "a person who tans animal skins to make leather", "sentence": "The tanner is dyeing animal skins.", "sentence_trans": "\u97a3\u9769\u5de5\u4eba\u6b63\u7ed9\u52a8\u7269\u76ae\u9769\u67d3\u8272\u3002", "sentence_phrase": "", "word_etyma": "tan\u97a3\u6599 + n + er\u540d\u8bcd\u540e\u7f00 \u2192 tanner \u5236\u97a3\u5de5\u4eba", "cloze_data": {"syllable": "tan-ner", "cloze": "tann[er]", "options": ["ar|ir|or|ur|a"], "tips": [["retann[er]"]]}}